fractal_faim_ipa/__FRACTAL_MANIFEST__.json
fractal_faim_ipa/__init__.py
fractal_faim_ipa/convert_cellvoyager_to_ome_zarr.py
fractal_faim_ipa/convert_md_to_ome_zarr.py
fractal_faim_ipa/converter_utils.py
fractal_faim_ipa/md_converter_utils.py
fractal_faim_ipa/py.typed
fractal_faim_ipa/roi_tables.py
fractal_faim_ipa/test_plate_simon.ipynb
fractal_faim_ipa/dev/task_list.py
fractal_faim_ipa/dev/task_info/md_converter.md
fractal_faim_ipa-0.6.3.dist-info/METADATA
fractal_faim_ipa-0.6.3.dist-info/WHEEL
fractal_faim_ipa-0.6.3.dist-info/licenses/LICENSE
fractal_faim_ipa-0.6.3.dist-info/RECORD
