Metadata-Version: 2.4
Name: fractal-faim-ipa
Version: 0.6.3
Summary: Provides Fractal tasks for the MD to OME-Zarr conversion of faim-ipa
Project-URL: homepage, https://github.com/fractal-analytics-platform/fractal-faim-ipa
Project-URL: repository, https://github.com/fractal-analytics-platform/fractal-faim-ipa
Author-email: Joel Luethi <joel.luethi@uzh.ch>
License: BSD-3-Clause
License-File: LICENSE
Classifier: Development Status :: 3 - Alpha
Classifier: Programming Language :: Python :: 3
Classifier: Programming Language :: Python :: 3.11
Classifier: Programming Language :: Python :: 3.12
Requires-Python: >=3.11
Requires-Dist: faim-ipa==0.13.0
Requires-Dist: fractal-task-tools>=0.1.1
Requires-Dist: fractal-tasks-core==1.5.6
Requires-Dist: pydantic
Requires-Dist: zarr
Provides-Extra: dev
Requires-Dist: black; extra == 'dev'
Requires-Dist: devtools; extra == 'dev'
Requires-Dist: ipython; extra == 'dev'
Requires-Dist: mypy; extra == 'dev'
Requires-Dist: pdbpp; extra == 'dev'
Requires-Dist: pre-commit; extra == 'dev'
Requires-Dist: rich; extra == 'dev'
Requires-Dist: ruff; extra == 'dev'
Provides-Extra: test
Requires-Dist: devtools; extra == 'test'
Requires-Dist: jsonschema; extra == 'test'
Requires-Dist: pooch; extra == 'test'
Requires-Dist: pytest; extra == 'test'
Requires-Dist: pytest-cov; extra == 'test'
